jailbreak/__init__.py
jailbreak/main.py
jailbreak-0.1.0.dist-info/LICENSE
jailbreak-0.1.0.dist-info/METADATA
jailbreak-0.1.0.dist-info/WHEEL
jailbreak-0.1.0.dist-info/RECORD
